{
  "updated_at": "2026-07-23T07:04:19.395+08:00",
  "fetch_time": "10:00",
  "categories": {
    "xunyee_check": {
      "name": "寻艺点赞",
      "icon": "👍",
      "sort_field": "value",
      "sort_order": "desc",
      "items": [
        {
          "name": "王橹杰",
          "person_id": 198331,
          "value": 2273,
          "prev_value": 18054,
          "change_amount": -15781,
          "change_percent": -87.4
        },
        {
          "name": "杨博文",
          "person_id": 198332,
          "value": 931,
          "prev_value": 10783,
          "change_amount": -9852,
          "change_percent": -91.4
        },
        {
          "name": "张桂源",
          "person_id": 198330,
          "value": 838,
          "prev_value": 5787,
          "change_amount": -4949,
          "change_percent": -85.5
        },
        {
          "name": "李煜东",
          "person_id": 198342,
          "value": 256,
          "prev_value": 1963,
          "change_amount": -1707,
          "change_percent": -87
        }
      ]
    }
  }
}
