{
  "updated_at": "2026-07-24T14:26:29.646+08:00",
  "fetch_time": "22:00",
  "categories": {
    "xunyee_check": {
      "name": "寻艺点赞",
      "icon": "👍",
      "sort_field": "value",
      "sort_order": "desc",
      "items": [
        {
          "name": "王橹杰",
          "person_id": 198331,
          "value": 7042,
          "prev_value": 4597,
          "change_amount": 2445,
          "change_percent": 53.2
        },
        {
          "name": "杨博文",
          "person_id": 198332,
          "value": 5857,
          "prev_value": 2056,
          "change_amount": 3801,
          "change_percent": 184.9
        },
        {
          "name": "张桂源",
          "person_id": 198330,
          "value": 2413,
          "prev_value": 1642,
          "change_amount": 771,
          "change_percent": 47
        },
        {
          "name": "李煜东",
          "person_id": 198342,
          "value": 833,
          "prev_value": 575,
          "change_amount": 258,
          "change_percent": 44.9
        }
      ]
    }
  }
}
